appomni/threat/align_tools/__init__.py
appomni/threat/align_tools/align/AlignLexer.py
appomni/threat/align_tools/align/AlignListener.py
appomni/threat/align_tools/align/AlignParser.py
appomni/threat/align_tools/align/__init__.py
appomni/threat/align_tools/linter.py
appomni_align_tools-0.1.0.dist-info/METADATA
appomni_align_tools-0.1.0.dist-info/WHEEL
appomni_align_tools-0.1.0.dist-info/entry_points.txt
appomni_align_tools-0.1.0.dist-info/RECORD
