Metadata-Version: 2.1
Name: appomni-align-tools
Version: 0.1.0
Summary: Tooling for interacting with AppOmni's ALIGN Parsers
Author: AppOmni
Author-email: aopython@appomni.com
Requires-Python: >=3.12,<4.0
Classifier: License :: OSI Approved :: MIT License
Classifier: Programming Language :: Python :: 3
Classifier: Programming Language :: Python :: 3.12
Classifier: Topic :: Software Development :: Libraries
Requires-Dist: antlr4-python3-runtime (>=4.13.2,<5.0.0)
